hexit/__init__.py
hexit/__main__.py
hexit-1.0.2.dist-info/LICENSE
hexit-1.0.2.dist-info/METADATA
hexit-1.0.2.dist-info/WHEEL
hexit-1.0.2.dist-info/top_level.txt
hexit-1.0.2.dist-info/RECORD
